rswjax/__init__.py
rswjax/losses.py
rswjax/regularizers.py
rswjax/rsw.py
rswjax/solver.py
rswjax-1.2.0.dist-info/LICENSE
rswjax-1.2.0.dist-info/METADATA
rswjax-1.2.0.dist-info/WHEEL
rswjax-1.2.0.dist-info/RECORD
