Metadata-Version: 2.1
Name: rswjax
Version: 1.2.0
Summary: A jax implementation of optimal representative sample weighting
License: Apache-2.0
Author: Andrew Timm
Requires-Python: >=3.9,<3.12
Classifier: License :: OSI Approved :: Apache Software License
Classifier: Programming Language :: Python :: 3
Classifier: Programming Language :: Python :: 3.9
Classifier: Programming Language :: Python :: 3.10
Classifier: Programming Language :: Python :: 3.11
Requires-Dist: jax (>=0.4.21,<0.5.0)
Requires-Dist: jaxlib (>=0.4.21,<0.5.0)
Requires-Dist: ott-jax (>=0.4.5,<0.5.0)
Requires-Dist: pandas (>=2.1.4,<3.0.0)
Requires-Dist: qdldl (>=0.1.7.post0,<0.2.0)
